Metadata-Version: 2.1
Name: pandora-upload
Version: 1.0.6
Summary: pandora-upload is a commandline uploader for pan.do/ra
Home-page: https://code.0x2620.org/0x2620/pandora-upload
Author: j
Author-email: j@mailb.org
License: GPLv3
Classifier: Development Status :: 5 - Production/Stable
Classifier: Environment :: Console
Classifier: Operating System :: OS Independent
Classifier: Programming Language :: Python :: 3
Classifier: License :: OSI Approved :: GNU General Public License (GPL)
Requires-Dist: ox>=3
Requires-Dist: lxml
